<annotation>
  <folder>Human_hand</folder>
  <filename>102cfad40cde6c4e.jpg</filename>
  <path>C:\PycharmProjects\OIDv4_ToolKit\OID\Dataset\train\Human_hand\102cfad40cde6c4e.jpg</path>
  <source>
    <database>Unknown</database>
  </source>
  <size>
    <width>1024</width>
    <height>683</height>
    <depth>3</depth>
  </size>
  <segmented>0</segmented>
  <object>
    <name>Human_hand</name>
    <pose>Unspecified</pose>
    <truncated>0</truncated>
    <difficult>0</difficult>
    <bndbox>
      <xmin>561</xmin>
      <ymin>111</ymin>
      <xmax>771</xmax>
      <ymax>294</ymax>
    </bndbox>
  </object>
  <object>
    <name>Human_hand</name>
    <pose>Unspecified</pose>
    <truncated>0</truncated>
    <difficult>0</difficult>
    <bndbox>
      <xmin>95</xmin>
      <ymin>623</ymin>
      <xmax>219</xmax>
      <ymax>682</ymax>
    </bndbox>
  </object>
</annotation>
