<annotation>
  <folder>Human_hand</folder>
  <filename>e1d7c915e6a3b363.jpg</filename>
  <path>C:\PycharmProjects\OIDv4_ToolKit\OID\Dataset\train\Human_hand\e1d7c915e6a3b363.jpg</path>
  <source>
    <database>Unknown</database>
  </source>
  <size>
    <width>1024</width>
    <height>768</height>
    <depth>3</depth>
  </size>
  <segmented>0</segmented>
  <object>
    <name>Human_hand</name>
    <pose>Unspecified</pose>
    <truncated>0</truncated>
    <difficult>0</difficult>
    <bndbox>
      <xmin>673</xmin>
      <ymin>611</ymin>
      <xmax>737</xmax>
      <ymax>707</ymax>
    </bndbox>
  </object>
  <object>
    <name>Human_hand</name>
    <pose>Unspecified</pose>
    <truncated>0</truncated>
    <difficult>0</difficult>
    <bndbox>
      <xmin>915</xmin>
      <ymin>600</ymin>
      <xmax>995</xmax>
      <ymax>678</ymax>
    </bndbox>
  </object>
</annotation>
